npdep_http_client/__init__.py
npdep_http_client/__main__.py
npdep_http_client/args/Args.py
npdep_http_client/args/__init__.py
npdep_http_client/client/Client.py
npdep_http_client/client/__init__.py
npdep_http_client/output/Output.py
npdep_http_client/output/__init__.py
npdep_http_client/type/RequestType.py
npdep_http_client/type/__init__.py
npdep_http_client/util/Util.py
npdep_http_client/util/__init__.py
npdep_http_client-1.0.0.dist-info/METADATA
npdep_http_client-1.0.0.dist-info/WHEEL
npdep_http_client-1.0.0.dist-info/entry_points.txt
npdep_http_client-1.0.0.dist-info/top_level.txt
npdep_http_client-1.0.0.dist-info/RECORD
