Metadata-Version: 2.1
Name: npdep_http_client
Version: 1.0.0
Summary: A client to exfiltrate data through HTTP messages
Home-page: https://github.com/npdep/http-client
Author: npdep
Classifier: Operating System :: OS Independent 
Classifier: Programming Language :: Python :: 3 
